app/AWord.py
app/__init__.py
app/rocket.py
app/utils.py
rocket_vocab-0.0.3.data/data/data/3000words.json
rocket_vocab-0.0.3.data/data/data/process_3000words.json
rocket_vocab-0.0.3.dist-info/LICENSE.txt
rocket_vocab-0.0.3.dist-info/METADATA
rocket_vocab-0.0.3.dist-info/WHEEL
rocket_vocab-0.0.3.dist-info/entry_points.txt
rocket_vocab-0.0.3.dist-info/top_level.txt
rocket_vocab-0.0.3.dist-info/RECORD
