Metadata-Version: 2.1
Name: rocket-vocab
Version: 0.0.3
Summary: learing vocabulary on terminal
Home-page: https://github.com/huongnhdh/rocket-vocab
Author: huongnhd
Author-email: huong.nhdh@gmail.com
License: MIT
Download-URL: https://github.com/huongnhdh/rocket-vocab/archive/v001.tar.gz
Keywords: vocab,terminal,true color
Platform: UNKNOWN
Classifier: Development Status :: 4 - Beta
Classifier: Intended Audience :: Education
Classifier: Topic :: System :: System Shells
Classifier: License :: OSI Approved :: MIT License
Classifier: Programming Language :: Python :: 3
Classifier: Programming Language :: Python :: 3.4
Classifier: Programming Language :: Python :: 3.5
Classifier: Programming Language :: Python :: 3.6
